tests/__init__.py
torchdiy/__init__.py
torchdiy/activate.py
torchdiy/attention.py
torchdiy/cnn.py
torchdiy/dropout.py
torchdiy/gru.py
torchdiy/linear.py
torchdiy/loss.py
torchdiy/nn.py
torchdiy/optim.py
torchdiy/rnn.py
torchdiy/rnn_deepseek.py
torchdiy/transformer.py
torchdiy/utils.py
torchdiy/transformers/__init__.py
torchdiy/transformers/auto.py
torchdiy/transformers/gpt2.py
torchdiy/utils/__init__.py
torchdiy/utils/data.py
torchdiy-0.4.0.dist-info/LICENSE
torchdiy-0.4.0.dist-info/METADATA
torchdiy-0.4.0.dist-info/WHEEL
torchdiy-0.4.0.dist-info/top_level.txt
torchdiy-0.4.0.dist-info/RECORD
