Metadata-Version: 2.2
Name: torchdiy
Version: 0.4.0
Summary: A hobby project just like torch for learning how to design a deep learning framework.
Home-page: https://github.com/ccc-py/torchdiy
Author: ccc
Author-email: ccckmit@gmail.com
Classifier: Programming Language :: Python :: 3
Classifier: License :: OSI Approved :: MIT License
Classifier: Operating System :: OS Independent
Requires-Python: >=3.6
License-File: LICENSE
Requires-Dist: numpy
Requires-Dist: torch
Requires-Dist: transformers
Dynamic: author
Dynamic: author-email
Dynamic: classifier
Dynamic: description
Dynamic: description-content-type
Dynamic: home-page
Dynamic: requires-dist
Dynamic: requires-python
Dynamic: summary
